CHANGES.txt
README.txt
setup.cfg
setup.py
w20e/__init__.py
w20e.hitman.egg-info/PKG-INFO
w20e.hitman.egg-info/SOURCES.txt
w20e.hitman.egg-info/dependency_links.txt
w20e.hitman.egg-info/not-zip-safe
w20e.hitman.egg-info/requires.txt
w20e.hitman.egg-info/top_level.txt
w20e/hitman/__init__.py
w20e/hitman/events.py
w20e/hitman/utils.py
w20e/hitman/models/__init__.py
w20e/hitman/models/base.py
w20e/hitman/models/exceptions.py
w20e/hitman/tests/__init__.py
w20e/hitman/tests/base_model.py
w20e/hitman/tests/utils.py
w20e/hitman/views/__init__.py
w20e/hitman/views/base.py